simplebins/__init__.py
simplebins/cut.py
simplebins-0.3.1.dist-info/METADATA
simplebins-0.3.1.dist-info/WHEEL
simplebins-0.3.1.dist-info/RECORD
