Metadata-Version: 2.4
Name: simplebins
Version: 0.3.1
Summary: A lightweight Python package to discretize numeric values into bins, similar to pandas.cut(), but simpler and more intuitive.
License: MIT
Keywords: binning,discretization,data-preprocessing,pandas,utilities
Author: Marius Kaffai
Author-email: marius.kaffai.sowi@gmail.com
Requires-Python: >=3.10,<4.0
Classifier: License :: OSI Approved :: MIT License
Classifier: Programming Language :: Python :: 3
Classifier: Programming Language :: Python :: 3.10
Classifier: Programming Language :: Python :: 3.11
Classifier: Programming Language :: Python :: 3.12
Classifier: Programming Language :: Python :: 3.13
Classifier: Programming Language :: Python :: 3.14
Requires-Dist: numpy (>=2.0.0,<3.0.0)
Requires-Dist: pandas (>=2.2.3,<3.0.0)
Project-URL: Homepage, https://github.com/mariuzka/simplebins
Project-URL: Repository, https://github.com/mariuzka/simplebins
